nethsm/__init__.py
nethsm/backup.py
nethsm/py.typed
nethsm/client/__init__.py
nethsm/client/api_client.py
nethsm/client/api_response.py
nethsm/client/exceptions.py
nethsm/client/py.typed
nethsm/client/rest.py
nethsm/client/security_schemes.py
nethsm/client/server.py
nethsm/client/apis/__init__.py
nethsm/client/apis/path_to_api.py
nethsm/client/apis/tag_to_api.py
nethsm/client/apis/paths/__init__.py
nethsm/client/apis/paths/config_backup_passphrase.py
nethsm/client/apis/paths/config_logging.py
nethsm/client/apis/paths/config_network.py
nethsm/client/apis/paths/config_time.py
nethsm/client/apis/paths/config_tls_cert_pem.py
nethsm/client/apis/paths/config_tls_csr_pem.py
nethsm/client/apis/paths/config_tls_generate.py
nethsm/client/apis/paths/config_tls_public_pem.py
nethsm/client/apis/paths/config_unattended_boot.py
nethsm/client/apis/paths/config_unlock_passphrase.py
nethsm/client/apis/paths/health_alive.py
nethsm/client/apis/paths/health_ready.py
nethsm/client/apis/paths/health_state.py
nethsm/client/apis/paths/info.py
nethsm/client/apis/paths/keys.py
nethsm/client/apis/paths/keys_generate.py
nethsm/client/apis/paths/keys_key_id.py
nethsm/client/apis/paths/keys_key_id_cert.py
nethsm/client/apis/paths/keys_key_id_csr_pem.py
nethsm/client/apis/paths/keys_key_id_decrypt.py
nethsm/client/apis/paths/keys_key_id_encrypt.py
nethsm/client/apis/paths/keys_key_id_move.py
nethsm/client/apis/paths/keys_key_id_public_pem.py
nethsm/client/apis/paths/keys_key_id_restrictions_tags_tag.py
nethsm/client/apis/paths/keys_key_id_sign.py
nethsm/client/apis/paths/keys_key_prefix.py
nethsm/client/apis/paths/lock.py
nethsm/client/apis/paths/metrics.py
nethsm/client/apis/paths/namespaces.py
nethsm/client/apis/paths/namespaces_namespace_id.py
nethsm/client/apis/paths/provision.py
nethsm/client/apis/paths/random.py
nethsm/client/apis/paths/system_backup.py
nethsm/client/apis/paths/system_cancel_update.py
nethsm/client/apis/paths/system_commit_update.py
nethsm-2.0.1.dist-info/licenses/LICENSE
nethsm-2.0.1.dist-info/WHEEL
nethsm-2.0.1.dist-info/METADATA
nethsm-2.0.1.dist-info/RECORD
