Metadata-Version: 2.4
Name: nethsm
Version: 2.0.1
Summary: Python Library to manage NetHSM(s).
Author-email: Nitrokey <pypi@nitrokey.com>
Requires-Python: >=3.9
Classifier: License :: OSI Approved :: Apache Software License
License-File: LICENSE
Requires-Dist: certifi
Requires-Dist: cryptography >=41.0
Requires-Dist: python-dateutil
Requires-Dist: typing_extensions ~= 4.3.0
Requires-Dist: urllib3 >=2.0,<3
Requires-Dist: black >=22.1.0,<23 ; extra == "dev"
Requires-Dist: flake8 ; extra == "dev"
Requires-Dist: flit >=3.2,<4 ; extra == "dev"
Requires-Dist: ipython ; extra == "dev"
Requires-Dist: isort ; extra == "dev"
Requires-Dist: mypy >=1.4,<1.5 ; extra == "dev"
Requires-Dist: pytest ; extra == "dev"
Requires-Dist: pytest-reporter-html1 ; extra == "dev"
Requires-Dist: docker ; extra == "dev"
Requires-Dist: podman >=5,<6 ; extra == "dev"
Requires-Dist: pycryptodome ; extra == "dev"
Requires-Dist: requests <2.32.0 ; extra == "dev"
Requires-Dist: types-python-dateutil ; extra == "dev"
Requires-Dist: types-requests ; extra == "dev"
Requires-Dist: pytest-cov ; extra == "dev"
Requires-Dist: cryptography ; extra == "dev"
Requires-Dist: pyyaml ; extra == "dev"
Project-URL: Source, https://github.com/Nitrokey/nethsm-sdk-py
Provides-Extra: dev
